{
  "$schema": "http://json-schema.org/draft-07/schema#",
  "title": "\u0027Merkintä neuvottelun, tapaamisen tai yhteydenoton peruuntumisesta\u0027 JSON schema",
  "type": "object",
  "additionalProperties": false,
  "sosmeta": {
    "title": "\u0027Merkintä neuvottelun, tapaamisen tai yhteydenoton peruuntumisesta\u0027 JSON schema",
    "status": "Valmis",
    "documentDefinitionVersion": "2022-09-28",
    "dataComponentLibraryVersion": "2022-09-27",
    "oid": "1.2.246.537.6.1506.19006.2022.9.28",
    "documentType": "Asiakaskertomusmerkintä",
    "documentAuthor": "Ammattihenkilö",
    "documentSubject": "Sosiaalihuollon  palvelutehtäville yhteiset asiakasasiakirjat"
  },
  "required": [
    "merkinta_neuvottelun_tapaamisen_tai_yhteydenoton_peruuntumisesta"
  ],
  "properties": {
    "merkinta_neuvottelun_tapaamisen_tai_yhteydenoton_peruuntumisesta": {
      "type": "object",
      "additionalProperties": false,
      "sosmeta": {
        "name": [
          {
            "lang": "fi",
            "value": "Merkintä neuvottelun, tapaamisen tai yhteydenoton peruuntumisesta"
          },
          {
            "lang": "sv",
            "value": "Anteckning om inhibering av överläggning, möte eller kontakt"
          }
        ]
      },
      "required": [
        "asiakas",
        "asiakaskertomusmerkinta",
        "laatija"
      ],
      "properties": {
        "asiakas": {
          "type": "array",
          "minItems": 1,
          "items": {
            "type": "object",
            "additionalProperties": false,
            "sosmeta": {
              "name": [
                {
                  "lang": "fi",
                  "value": "Asiakas"
                },
                {
                  "lang": "sv",
                  "value": "Klient"
                }
              ],
              "description": [
                {
                  "lang": "fi",
                  "value": "Asiakas on henkilö, jonka asiaa peruuntunut neuvottelu, yhteydenotto tai tapaaminen koskee."
                },
                {
                  "lang": "sv",
                  "value": "Klienten är den person, vars ärende den överläggning, kontakt eller det möte som inhiberats gäller."
                }
              ],
              "repeatable": true,
              "required": true,
              "conditionalRequired": false,
              "nationwideRecordedInformation": false,
              "hiddenField": false,
              "hiddenTitle": false,
              "rowNumber": 1
            },
            "required": [
              "sukunimi",
              "etunimet"
            ],
            "properties": {
              "sukunimi": {
                "type": "string",
                "minLength": 1,
                "sosmeta": {
                  "name": [
                    {
                      "lang": "fi",
                      "value": "Sukunimi"
                    },
                    {
                      "lang": "sv",
                      "value": "Efternamn"
                    }
                  ],
                  "description": [
                    {
                      "lang": "fi",
                      "value": "-"
                    },
                    {
                      "lang": "sv",
                      "value": "-"
                    }
                  ],
                  "representation": [
                    {
                      "lang": "fi",
                      "value": "Nimi"
                    },
                    {
                      "lang": "sv",
                      "value": "Namn"
                    }
                  ],
                  "repeatable": false,
                  "required": true,
                  "conditionalRequired": false,
                  "nationwideRecordedInformation": false,
                  "hiddenField": false,
                  "hiddenTitle": false,
                  "rowNumber": 2
                }
              },
              "etunimet": {
                "type": "string",
                "minLength": 1,
                "sosmeta": {
                  "name": [
                    {
                      "lang": "fi",
                      "value": "Etunimet"
                    },
                    {
                      "lang": "sv",
                      "value": "Samtliga förnamn"
                    }
                  ],
                  "description": [
                    {
                      "lang": "fi",
                      "value": "-"
                    },
                    {
                      "lang": "sv",
                      "value": "-"
                    }
                  ],
                  "representation": [
                    {
                      "lang": "fi",
                      "value": "Nimi"
                    },
                    {
                      "lang": "sv",
                      "value": "Namn"
                    }
                  ],
                  "repeatable": false,
                  "required": true,
                  "conditionalRequired": false,
                  "nationwideRecordedInformation": false,
                  "hiddenField": false,
                  "hiddenTitle": false,
                  "rowNumber": 3
                }
              },
              "henkilotunnus": {
                "type": "object",
                "additionalProperties": false,
                "sosmeta": {
                  "name": [
                    {
                      "lang": "fi",
                      "value": "Henkilötunnus"
                    },
                    {
                      "lang": "sv",
                      "value": "Personbeteckning"
                    }
                  ],
                  "description": [
                    {
                      "lang": "fi",
                      "value": "-"
                    },
                    {
                      "lang": "sv",
                      "value": "-"
                    }
                  ],
                  "implementationNote": [
                    {
                      "lang": "fi",
                      "value": "Ehdollisesti pakollinen: Toinen kentistä Henkilötunnus ja Tilapäinen yksilöintitunnus on pakollinen."
                    },
                    {
                      "lang": "sv",
                      "value": "Ehdollisesti pakollinen: Toinen kentistä Henkilötunnus ja Tilapäinen yksilöintitunnus on pakollinen."
                    }
                  ],
                  "representation": [
                    {
                      "lang": "fi",
                      "value": "Tunnus"
                    },
                    {
                      "lang": "sv",
                      "value": "Identifierare"
                    }
                  ],
                  "systemUri": [
                    {
                      "lang": "",
                      "value": "urn:oid:1.2.246.21"
                    }
                  ],
                  "repeatable": false,
                  "required": false,
                  "conditionalRequired": true,
                  "nationwideRecordedInformation": false,
                  "hiddenField": false,
                  "hiddenTitle": false,
                  "rowNumber": 4
                },
                "required": [
                  "value"
                ],
                "properties": {
                  "system": {
                    "type": "string"
                  },
                  "value": {
                    "type": "string"
                  }
                }
              },
              "tilapainen_yksilointitunnus": {
                "type": "object",
                "additionalProperties": false,
                "sosmeta": {
                  "name": [
                    {
                      "lang": "fi",
                      "value": "Tilapäinen yksilöintitunnus"
                    },
                    {
                      "lang": "sv",
                      "value": "Temporär identifikationskod"
                    }
                  ],
                  "description": [
                    {
                      "lang": "fi",
                      "value": "Kenttään kirjataan henkilön tilapäiseen yksilöintiin annettu tunnus."
                    },
                    {
                      "lang": "sv",
                      "value": "I fältet antecknas identifikationskoden som getts personen för tillfällig identifiering."
                    }
                  ],
                  "example": [
                    {
                      "lang": "fi",
                      "value": "112233-445a"
                    },
                    {
                      "lang": "sv",
                      "value": "112233-445a"
                    }
                  ],
                  "implementationNote": [
                    {
                      "lang": "fi",
                      "value": "Ehdollisesti pakollinen: Toinen kentistä Henkilötunnus ja Tilapäinen yksilöintitunnus on pakollinen."
                    },
                    {
                      "lang": "sv",
                      "value": "Ehdollisesti pakollinen: Toinen kentistä Henkilötunnus ja Tilapäinen yksilöintitunnus on pakollinen."
                    }
                  ],
                  "representation": [
                    {
                      "lang": "fi",
                      "value": "Tunnus"
                    },
                    {
                      "lang": "sv",
                      "value": "Identifierare"
                    }
                  ],
                  "repeatable": false,
                  "required": false,
                  "conditionalRequired": true,
                  "nationwideRecordedInformation": false,
                  "hiddenField": false,
                  "hiddenTitle": false,
                  "rowNumber": 5
                },
                "required": [
                  "value"
                ],
                "properties": {
                  "system": {
                    "type": "string"
                  },
                  "value": {
                    "type": "string"
                  }
                }
              }
            }
          }
        },
        "asiakaskertomusmerkinta": {
          "type": "object",
          "additionalProperties": false,
          "sosmeta": {
            "name": [
              {
                "lang": "fi",
                "value": "Asiakaskertomusmerkintä"
              },
              {
                "lang": "sv",
                "value": "Anteckning i en klientjournal"
              }
            ],
            "description": [
              {
                "lang": "fi",
                "value": "-"
              },
              {
                "lang": "sv",
                "value": "-"
              }
            ],
            "repeatable": false,
            "required": true,
            "conditionalRequired": false,
            "nationwideRecordedInformation": false,
            "hiddenField": true,
            "hiddenTitle": false,
            "rowNumber": 6
          },
          "required": [
            "palvelutehtava"
          ],
          "properties": {
            "palvelutehtava": {
              "type": "object",
              "additionalProperties": false,
              "sosmeta": {
                "name": [
                  {
                    "lang": "fi",
                    "value": "Palvelutehtävä"
                  },
                  {
                    "lang": "sv",
                    "value": "Serviceuppgift"
                  }
                ],
                "description": [
                  {
                    "lang": "fi",
                    "value": "Kenttään kirjataan luokituksen avulla palvelutehtävä, johon asiakaskertomusmerkintä kuuluu."
                  },
                  {
                    "lang": "sv",
                    "value": "I fältet antecknas serviceuppgiften, till vilken anteckningen i klientjournalen hänför sig."
                  }
                ],
                "classification": [
                  {
                    "lang": "fi",
                    "value": "Koodistopalvelin: Sosiaalihuolto - Palvelutehtävä 1.2.246.537.6.1221"
                  },
                  {
                    "lang": "sv",
                    "value": "Kodtjänsten: Socialvård - Serviceuppgift 1.2.246.537.6.1221"
                  }
                ],
                "classificationLink": [
                  {
                    "lang": "",
                    "value": "https://koodistopalvelu.kanta.fi/codeserver/pages/classification-view-page.xhtml?classificationKey\u003d704\u0026versionKey\u003d2563"
                  }
                ],
                "classificationOid": [
                  {
                    "lang": "",
                    "value": "1.2.246.537.6.1221"
                  }
                ],
                "representation": [
                  {
                    "lang": "fi",
                    "value": "Koodi"
                  },
                  {
                    "lang": "sv",
                    "value": "Kod"
                  }
                ],
                "repeatable": false,
                "required": true,
                "conditionalRequired": false,
                "nationwideRecordedInformation": false,
                "hiddenField": false,
                "hiddenTitle": false,
                "rowNumber": 7
              },
              "required": [
                "system",
                "code",
                "display"
              ],
              "properties": {
                "system": {
                  "type": "string",
                  "pattern": "^urn:oid:1\\.2\\.246\\.537\\.6\\.1221(\\.\\d+)*$"
                },
                "code": {
                  "type": "string"
                },
                "display": {
                  "type": "string"
                }
              }
            },
            "sosiaalipalvelu": {
              "type": "array",
              "minItems": 0,
              "items": {
                "type": "object",
                "additionalProperties": false,
                "sosmeta": {
                  "name": [
                    {
                      "lang": "fi",
                      "value": "Sosiaalipalvelu"
                    },
                    {
                      "lang": "sv",
                      "value": "Socialservice"
                    }
                  ],
                  "description": [
                    {
                      "lang": "fi",
                      "value": "Kenttään kirjataan luokituksen avulla sosiaalipalvelu, jonka antamiseen asiakaskertomusmerkintä liittyy."
                    },
                    {
                      "lang": "sv",
                      "value": "I fältet antecknas socialservicen, till vilken anteckningen i klientjournalen hänför sig."
                    }
                  ],
                  "classification": [
                    {
                      "lang": "fi",
                      "value": "Koodistopalvelin: Sosiaalihuolto - Sosiaalipalvelut 1.2.246.537.6.1222"
                    },
                    {
                      "lang": "sv",
                      "value": "Kodtjänsten: Socialvård - Socialservice 1.2.246.537.6.1222"
                    }
                  ],
                  "classificationLink": [
                    {
                      "lang": "",
                      "value": "https://koodistopalvelu.kanta.fi/codeserver/pages/classification-view-page.xhtml?classificationKey\u003d703\u0026versionKey\u003d2683"
                    }
                  ],
                  "classificationOid": [
                    {
                      "lang": "",
                      "value": "1.2.246.537.6.1222"
                    }
                  ],
                  "representation": [
                    {
                      "lang": "fi",
                      "value": "Koodi"
                    },
                    {
                      "lang": "sv",
                      "value": "Kod"
                    }
                  ],
                  "repeatable": true,
                  "required": false,
                  "conditionalRequired": false,
                  "nationwideRecordedInformation": false,
                  "hiddenField": false,
                  "hiddenTitle": false,
                  "rowNumber": 8
                },
                "required": [
                  "system",
                  "code",
                  "display"
                ],
                "properties": {
                  "system": {
                    "type": "string",
                    "pattern": "^urn:oid:1\\.2\\.246\\.537\\.6\\.1222(\\.\\d+)*$"
                  },
                  "code": {
                    "type": "string"
                  },
                  "display": {
                    "type": "string"
                  }
                }
              }
            },
            "tapahtuma": {
              "type": "object",
              "additionalProperties": false,
              "sosmeta": {
                "name": [
                  {
                    "lang": "fi",
                    "value": "Tapahtuma"
                  },
                  {
                    "lang": "sv",
                    "value": "Händelse"
                  }
                ],
                "description": [
                  {
                    "lang": "fi",
                    "value": "-"
                  },
                  {
                    "lang": "sv",
                    "value": "-"
                  }
                ],
                "repeatable": false,
                "required": false,
                "conditionalRequired": false,
                "nationwideRecordedInformation": false,
                "hiddenField": true,
                "hiddenTitle": false,
                "rowNumber": 9
              },
              "required": [],
              "properties": {
                "paivamaara_ja_kellonaika": {
                  "type": "string",
                  "pattern": "^-?[0-9]{4}(-(0[1-9]|1[0-2])(-(0[0-9]|[1-2][0-9]|3[0-1])(T([01][0-9]|2[0-3]):[0-5][0-9]:[0-5][0-9](\\.[0-9]+)?(Z|(\\+|-)((0[0-9]|1[0-3]):[0-5][0-9]|14:00)))?)?)?$",
                  "sosmeta": {
                    "name": [
                      {
                        "lang": "fi",
                        "value": "Päivämäärä ja kellonaika"
                      },
                      {
                        "lang": "sv",
                        "value": "Datum och klockslag"
                      }
                    ],
                    "title": [
                      {
                        "lang": "fi",
                        "value": "Peruuntuneen neuvottelun, tapaamisen tai yhteydenoton sovittu ajankohta"
                      },
                      {
                        "lang": "sv",
                        "value": "Överenskommen tidpunkt för överläggning, möte eller kontakt som inhiberats"
                      }
                    ],
                    "description": [
                      {
                        "lang": "fi",
                        "value": "-"
                      },
                      {
                        "lang": "sv",
                        "value": "-"
                      }
                    ],
                    "representation": [
                      {
                        "lang": "fi",
                        "value": "Hetki"
                      },
                      {
                        "lang": "sv",
                        "value": "Datum och klockslag"
                      }
                    ],
                    "repeatable": false,
                    "required": false,
                    "conditionalRequired": false,
                    "nationwideRecordedInformation": false,
                    "hiddenField": false,
                    "hiddenTitle": false,
                    "rowNumber": 10
                  }
                },
                "asiointitapa": {
                  "type": "array",
                  "minItems": 0,
                  "items": {
                    "type": "object",
                    "additionalProperties": false,
                    "sosmeta": {
                      "name": [
                        {
                          "lang": "fi",
                          "value": "Asiointitapa"
                        },
                        {
                          "lang": "sv",
                          "value": "Typ av kontakt"
                        }
                      ],
                      "title": [
                        {
                          "lang": "fi",
                          "value": "Neuvottelu-, tapaamis- tai yhteydenottotapa"
                        },
                        {
                          "lang": "sv",
                          "value": "Överläggnings-, mötes- eller kontakttyp"
                        }
                      ],
                      "description": [
                        {
                          "lang": "fi",
                          "value": "Kenttään kirjataan luokituksen avulla asiointitapa."
                        },
                        {
                          "lang": "sv",
                          "value": "I fältet antecknas typen av kontakt med hjälp av klassificeringen."
                        }
                      ],
                      "example": [
                        {
                          "lang": "fi",
                          "value": "3 \u003d Käynti asiakkaan luona"
                        },
                        {
                          "lang": "sv",
                          "value": "3 \u003d Besök hos klienten"
                        }
                      ],
                      "classification": [
                        {
                          "lang": "fi",
                          "value": "Koodistopalvelin: Sosiaalihuolto - Asiointitapa 1.2.246.537.6.1250"
                        },
                        {
                          "lang": "sv",
                          "value": "Kodtjänsten: Socialvård - Typ av kontakt med klienten 1.2.246.537.6.1250"
                        }
                      ],
                      "classificationLink": [
                        {
                          "lang": "",
                          "value": "https://koodistopalvelu.kanta.fi/codeserver/pages/classification-view-page.xhtml?classificationKey\u003d1803\u0026versionKey\u003d2043"
                        }
                      ],
                      "classificationOid": [
                        {
                          "lang": "",
                          "value": "1.2.246.537.6.1250"
                        }
                      ],
                      "representation": [
                        {
                          "lang": "fi",
                          "value": "Koodi"
                        },
                        {
                          "lang": "sv",
                          "value": "Kod"
                        }
                      ],
                      "repeatable": true,
                      "required": false,
                      "conditionalRequired": false,
                      "nationwideRecordedInformation": false,
                      "hiddenField": false,
                      "hiddenTitle": false,
                      "rowNumber": 11
                    },
                    "required": [
                      "system",
                      "code",
                      "display"
                    ],
                    "properties": {
                      "system": {
                        "type": "string",
                        "pattern": "^urn:oid:1\\.2\\.246\\.537\\.6\\.1250(\\.\\d+)*$"
                      },
                      "code": {
                        "type": "string"
                      },
                      "display": {
                        "type": "string"
                      }
                    }
                  }
                },
                "peruuntumisen_syy": {
                  "type": "object",
                  "additionalProperties": false,
                  "sosmeta": {
                    "name": [
                      {
                        "lang": "fi",
                        "value": "Peruuntumisen syy"
                      },
                      {
                        "lang": "sv",
                        "value": "Orsak till annulleringen"
                      }
                    ],
                    "description": [
                      {
                        "lang": "fi",
                        "value": "-"
                      },
                      {
                        "lang": "sv",
                        "value": "-"
                      }
                    ],
                    "classification": [
                      {
                        "lang": "fi",
                        "value": "THL - Palvelutapahtuman peruuntumisen tai siirtymisen syy 1.2.246.537.6.126"
                      }
                    ],
                    "classificationLink": [
                      {
                        "lang": "",
                        "value": "https://koodistopalvelu.kanta.fi/codeserver/pages/classification-view-page.xhtml?classificationKey\u003d309\u0026versionKey\u003d386"
                      }
                    ],
                    "classificationOid": [
                      {
                        "lang": "",
                        "value": "1.2.246.537.6.126"
                      }
                    ],
                    "valueSet": [
                      {
                        "lang": "fi",
                        "value": "Y30 \u003d Asiakkaasta johtuva syy,\nY32 \u003d Organisaatiosta johtuva syy"
                      }
                    ],
                    "representation": [
                      {
                        "lang": "fi",
                        "value": "Koodi"
                      },
                      {
                        "lang": "sv",
                        "value": "Kod"
                      }
                    ],
                    "repeatable": false,
                    "required": false,
                    "conditionalRequired": false,
                    "nationwideRecordedInformation": false,
                    "hiddenField": false,
                    "hiddenTitle": false,
                    "acceptedValues": [
                      {
                        "lang": "",
                        "value": "Y30"
                      },
                      {
                        "lang": "",
                        "value": "Y32"
                      }
                    ],
                    "rowNumber": 12
                  },
                  "required": [
                    "system",
                    "code",
                    "display"
                  ],
                  "properties": {
                    "system": {
                      "type": "string",
                      "pattern": "^urn:oid:1\\.2\\.246\\.537\\.6\\.126(\\.\\d+)*$"
                    },
                    "code": {
                      "type": "string",
                      "enum": [
                        "Y30",
                        "Y32"
                      ]
                    },
                    "display": {
                      "type": "string"
                    }
                  }
                },
                "lisatiedot_peruuntumisesta": {
                  "type": "string",
                  "sosmeta": {
                    "name": [
                      {
                        "lang": "fi",
                        "value": "Lisätiedot peruuntumisesta"
                      },
                      {
                        "lang": "sv",
                        "value": "Tilläggsuppgifter om annulleringen"
                      }
                    ],
                    "description": [
                      {
                        "lang": "fi",
                        "value": "Kenttään voidaan kuvata peruuntumisen syitä tarkemmin. Jos esim. neuvottelun peruuntuminen johtui siitä, että neuvotteluun kutsuttu muu taho joutui perumaan osallistumisen, asia voidaan kirjata tähän kenttään."
                      },
                      {
                        "lang": "sv",
                        "value": "I fältet kan beskrivas detaljerade orsaker till annulleringen. Om t.ex. en överläggning annulleras på grund av att en samkallad part blir förhindrad att delta, kan denna orsak antecknas i fältet."
                      }
                    ],
                    "example": [
                      {
                        "lang": "fi",
                        "value": "Asiakas perui tapaamisen sairastumisen vuoksi."
                      },
                      {
                        "lang": "sv",
                        "value": "Klienten annullerade tiden på grund av att hon blivit sjuk."
                      }
                    ],
                    "representation": [
                      {
                        "lang": "fi",
                        "value": "Teksti"
                      },
                      {
                        "lang": "sv",
                        "value": "Text"
                      }
                    ],
                    "repeatable": false,
                    "required": false,
                    "conditionalRequired": false,
                    "nationwideRecordedInformation": false,
                    "hiddenField": false,
                    "hiddenTitle": false,
                    "rowNumber": 13
                  }
                }
              }
            }
          }
        },
        "paivamaara": {
          "type": "string",
          "pattern": "^-?[0-9]{4}(-(0[1-9]|1[0-2])(-(0[0-9]|[1-2][0-9]|3[0-1]))?)?$",
          "sosmeta": {
            "name": [
              {
                "lang": "fi",
                "value": "Päivämäärä"
              },
              {
                "lang": "sv",
                "value": "Datum"
              }
            ],
            "description": [
              {
                "lang": "fi",
                "value": "Kenttään kirjataan asiakaskertomusmerkinnän laatimisen päivämäärä."
              },
              {
                "lang": "sv",
                "value": "I fältet antecknas datum för anteckningen i klientjournalen."
              }
            ],
            "representation": [
              {
                "lang": "fi",
                "value": "Pvm"
              },
              {
                "lang": "sv",
                "value": "Datum"
              }
            ],
            "repeatable": false,
            "required": false,
            "conditionalRequired": false,
            "nationwideRecordedInformation": false,
            "hiddenField": false,
            "hiddenTitle": false,
            "rowNumber": 14
          }
        },
        "laatija": {
          "type": "object",
          "additionalProperties": false,
          "sosmeta": {
            "name": [
              {
                "lang": "fi",
                "value": "Laatija"
              },
              {
                "lang": "sv",
                "value": "Upprättare"
              }
            ],
            "description": [
              {
                "lang": "fi",
                "value": "Laatija on asiakaskertomusmerkinnän laatinut ammattihenkilö."
              },
              {
                "lang": "sv",
                "value": "Upprättare är den yrkesutbildade person som har upprättat anteckningen i klientjournalen."
              }
            ],
            "repeatable": false,
            "required": true,
            "conditionalRequired": false,
            "nationwideRecordedInformation": false,
            "hiddenField": false,
            "hiddenTitle": false,
            "rowNumber": 15
          },
          "required": [
            "sukunimi",
            "etunimet"
          ],
          "properties": {
            "sukunimi": {
              "type": "string",
              "minLength": 1,
              "sosmeta": {
                "name": [
                  {
                    "lang": "fi",
                    "value": "Sukunimi"
                  },
                  {
                    "lang": "sv",
                    "value": "Efternamn"
                  }
                ],
                "description": [
                  {
                    "lang": "fi",
                    "value": "-"
                  },
                  {
                    "lang": "sv",
                    "value": "-"
                  }
                ],
                "representation": [
                  {
                    "lang": "fi",
                    "value": "Nimi"
                  },
                  {
                    "lang": "sv",
                    "value": "Namn"
                  }
                ],
                "repeatable": false,
                "required": true,
                "conditionalRequired": false,
                "nationwideRecordedInformation": false,
                "hiddenField": false,
                "hiddenTitle": false,
                "rowNumber": 16
              }
            },
            "etunimet": {
              "type": "string",
              "minLength": 1,
              "sosmeta": {
                "name": [
                  {
                    "lang": "fi",
                    "value": "Etunimet"
                  },
                  {
                    "lang": "sv",
                    "value": "Samtliga förnamn"
                  }
                ],
                "description": [
                  {
                    "lang": "fi",
                    "value": "-"
                  },
                  {
                    "lang": "sv",
                    "value": "-"
                  }
                ],
                "representation": [
                  {
                    "lang": "fi",
                    "value": "Nimi"
                  },
                  {
                    "lang": "sv",
                    "value": "Namn"
                  }
                ],
                "repeatable": false,
                "required": true,
                "conditionalRequired": false,
                "nationwideRecordedInformation": false,
                "hiddenField": false,
                "hiddenTitle": false,
                "rowNumber": 17
              }
            },
            "tehtavanimike": {
              "type": "string",
              "sosmeta": {
                "name": [
                  {
                    "lang": "fi",
                    "value": "Tehtävänimike"
                  },
                  {
                    "lang": "sv",
                    "value": "Uppgiftsbeteckning"
                  }
                ],
                "description": [
                  {
                    "lang": "fi",
                    "value": "-"
                  },
                  {
                    "lang": "sv",
                    "value": "-"
                  }
                ],
                "example": [
                  {
                    "lang": "fi",
                    "value": "-"
                  },
                  {
                    "lang": "sv",
                    "value": "-"
                  }
                ],
                "representation": [
                  {
                    "lang": "fi",
                    "value": "Teksti"
                  },
                  {
                    "lang": "sv",
                    "value": "Text"
                  }
                ],
                "repeatable": false,
                "required": false,
                "conditionalRequired": false,
                "nationwideRecordedInformation": false,
                "hiddenField": false,
                "hiddenTitle": false,
                "rowNumber": 18
              }
            },
            "palveluyksikko": {
              "type": "object",
              "additionalProperties": false,
              "sosmeta": {
                "name": [
                  {
                    "lang": "fi",
                    "value": "Palveluyksikkö"
                  },
                  {
                    "lang": "sv",
                    "value": "Serviceenhet"
                  }
                ],
                "description": [
                  {
                    "lang": "fi",
                    "value": "Kenttään kirjataan palveluyksikön nimi SOTE-organisaatiorekisterin avulla."
                  },
                  {
                    "lang": "sv",
                    "value": "I fältet antecknas namnet på serviceenheten enligt Organisationsregistret för social- och hälsovården."
                  }
                ],
                "example": [
                  {
                    "lang": "fi",
                    "value": "1.2.246.10.1012636.10.1.1.100768 \u003d Espoon keskuksen lastensuojelu, Espoon kaupunki, sosiaali- ja terveystoimi"
                  },
                  {
                    "lang": "sv",
                    "value": "1.2.246.10.1012636.10.1.1.100768 \u003d Esbo centrums barnskydd, Esbo stad, social- och hälsovårdssektorn"
                  }
                ],
                "classification": [
                  {
                    "lang": "fi",
                    "value": "Koodistopalvelin: THL - SOTE-organisaatiorekisteri 1.2.246.537.6.202"
                  },
                  {
                    "lang": "sv",
                    "value": "Kodtjänsten: THL - SOTE-organisationsregister 1.2.246.537.6.202"
                  }
                ],
                "classificationLink": [
                  {
                    "lang": "",
                    "value": "https://koodistopalvelu.kanta.fi/codeserver/pages/classification-view-page.xhtml?classificationKey\u003d421\u0026versionKey\u003d501"
                  }
                ],
                "classificationOid": [
                  {
                    "lang": "",
                    "value": "1.2.246.537.6.202"
                  }
                ],
                "representation": [
                  {
                    "lang": "fi",
                    "value": "Koodi"
                  },
                  {
                    "lang": "sv",
                    "value": "Kod"
                  }
                ],
                "repeatable": false,
                "required": false,
                "conditionalRequired": false,
                "nationwideRecordedInformation": false,
                "hiddenField": false,
                "hiddenTitle": false,
                "rowNumber": 19
              },
              "required": [
                "system",
                "code",
                "display"
              ],
              "properties": {
                "system": {
                  "type": "string",
                  "pattern": "^urn:oid:1\\.2\\.246\\.537\\.6\\.202(\\.\\d+)*$"
                },
                "code": {
                  "type": "string"
                },
                "display": {
                  "type": "string"
                }
              }
            }
          }
        }
      }
    }
  }
}